iopenscad/__init__.py
iopenscad/__main__.py
iopenscad/favicon.png
iopenscad/install.py
iopenscad/kernel.json
iopenscad/kernel.py
iopenscad/logo-32x32.png
iopenscad/logo-64x64.png
iopenscad/parser.py
iopenscad/scanner.py
iopenscad/test.py
pschatzmann_test_001-1.0.9.dist-info/METADATA
pschatzmann_test_001-1.0.9.dist-info/WHEEL
pschatzmann_test_001-1.0.9.dist-info/top_level.txt
pschatzmann_test_001-1.0.9.dist-info/RECORD
