Metadata-Version: 2.1
Name: pschatzmann-test-001
Version: 1.0.9
Summary: Jupyter kernel for OpenSCAD
Home-page: https://github.com/pschatzmann/openscad-kernel
Author: Phil Schatzmann
Author-email: phil.schatzmann@gmail.com
License: MIT
Platform: UNKNOWN
Classifier: License :: OSI Approved :: MIT License
Classifier: Programming Language :: Python :: 3
Classifier: Programming Language :: Python :: 3.7
